lttbc.cpython-311-aarch64-linux-gnu.so
plttbc-0.2.4.dist-info/top_level.txt
plttbc-0.2.4.dist-info/WHEEL
plttbc-0.2.4.dist-info/METADATA
plttbc-0.2.4.dist-info/LICENSE.txt
plttbc-0.2.4.dist-info/RECORD
